gqylpy_command/__init__.py
gqylpy_command/g command.py
gqylpy_command-1.1.1.dist-info/LICENSE
gqylpy_command-1.1.1.dist-info/METADATA
gqylpy_command-1.1.1.dist-info/WHEEL
gqylpy_command-1.1.1.dist-info/top_level.txt
gqylpy_command-1.1.1.dist-info/RECORD
