Metadata-Version: 2.1
Name: gqylpy_command
Version: 1.1.1
Summary: 调用系统命令，基于内置库 subprocess。并提供了多种用于判断命令调用结果是否如期的方法。
Home-page: http://gqylpy.com
Author: 竹永康
Author-email: <gqylpy@outlook.com>
License: Apache 2.0
Project-URL: Source, https://github.com/gqylpy/gqylpy-command
Classifier: Environment :: Web Environment
Classifier: Intended Audience :: Developers
Classifier: License :: OSI Approved :: Apache Software License
Classifier: Operating System :: OS Independent
Classifier: Topic :: Text Processing :: Indexing
Classifier: Topic :: Utilities
Classifier: Topic :: Internet
Classifier: Topic :: Software Development :: Libraries :: Python Modules
Classifier: Programming Language :: Python :: 3.6
Classifier: Programming Language :: Python :: 3.7
Classifier: Programming Language :: Python :: 3.8
Classifier: Programming Language :: Python :: 3.9
Classifier: Programming Language :: Python :: 3.10
Requires-Python: >=3.6, <4
License-File: LICENSE
